mofsynth_qm/__cli__.py
mofsynth_qm/__init__.py
mofsynth_qm/__main__.py
mofsynth_qm/__utils__.py
mofsynth_qm/modules/__init__.py
mofsynth_qm/modules/linkers.py
mofsynth_qm/modules/mof.py
mofsynth_qm/modules/other.py
mofsynth_qm-1.1.0.dist-info/licenses/LICENSE
mofsynth_qm-1.1.0.dist-info/METADATA
mofsynth_qm-1.1.0.dist-info/WHEEL
mofsynth_qm-1.1.0.dist-info/entry_points.txt
mofsynth_qm-1.1.0.dist-info/top_level.txt
mofsynth_qm-1.1.0.dist-info/RECORD
