Metadata-Version: 2.4
Name: mofsynth_qm
Version: 1.1.0
Summary: Package for MOF synthesizability evaluation.
Author-email: "Charalampos G. Livas" <livas.charalampos@gmail.com>
License: GPL-3.0-only
Project-URL: Homepage, https://github.com/livaschar/mofsynth_qm
Project-URL: Issues, https://github.com/livaschar/mofsynth_qm/issues
Project-URL: Documentation, https://mofsynth_qm.readthedocs.io/en/latest/
Classifier: Programming Language :: Python :: 3
Classifier: License :: OSI Approved :: GNU General Public License v3 (GPLv3)
Classifier: Operating System :: POSIX :: Linux
Requires-Python: >=3.10
License-File: LICENSE
Requires-Dist: matplotlib>=3.7.1
Requires-Dist: numpy>=1.24.1
Requires-Dist: pymatgen>=2023.5.10
Requires-Dist: openpyxl>=3.1.2
Requires-Dist: rmsd==1.5.1
Requires-Dist: pyyaml
Dynamic: license-file
